choixpeau/__init__.py
choixpeau/amplitude.py
choixpeau/choixpeau.py
choixpeau/decorators/__init__.py
choixpeau/decorators/fastapi.py
choixpeau-0.0.9.dist-info/LICENSE
choixpeau-0.0.9.dist-info/METADATA
choixpeau-0.0.9.dist-info/WHEEL
choixpeau-0.0.9.dist-info/top_level.txt
choixpeau-0.0.9.dist-info/RECORD
